LICENSE
scytale_cipher/__init__.py
scytale_cipher/scytale.py
scytale_cipher-0.1.2.dist-info/entry_points.txt
scytale_cipher-0.1.2.dist-info/LICENSE
scytale_cipher-0.1.2.dist-info/WHEEL
scytale_cipher-0.1.2.dist-info/METADATA
scytale_cipher-0.1.2.dist-info/RECORD
