Metadata-Version: 2.1
Name: scytale-cipher
Version: 0.1.2
Summary: Scytale cipher algorithm cli tool
Home-page: https://github.com/lockejan/scytale
License: Unlicense
Keywords: scytale,cipher,cli
Author: Jan Schmitt
Author-email: git@smittie.de
Maintainer: Jan Schmitt
Maintainer-email: git@smittie.de
Requires-Python: >=3.10,<4.0
Classifier: Environment :: Console
Classifier: Intended Audience :: Education
Classifier: License :: Other/Proprietary License
Classifier: Operating System :: OS Independent
Classifier: Programming Language :: Python :: 3
Classifier: Programming Language :: Python :: 3.10
Classifier: Programming Language :: Python :: 3.11
Classifier: Programming Language :: Python :: 3 :: Only
Classifier: Topic :: Text Processing
Classifier: Topic :: Utilities
Project-URL: Repository, https://github.com/lockejan/scytale
